{
  "_fv": 13,
  "_type": "recipe",
  "definition": {
    "recipeType": "Crafting",
    "xpReward": 0.0,
    "cookingTime": 200,
    "recipeRetstackSize": 1,
    "group": "debug_stick",
    "recipeShapeless": false,
    "recipeSlots": [
      {
        "value": "Items.NETHER_STAR"
      },
      {
        "value": "Items.NETHER_STAR"
      },
      {
        "value": "Items.NETHER_STAR"
      },
      {
        "value": "Items.NETHER_STAR"
      },
      {
        "value": "Items.STICK"
      },
      {
        "value": "Items.NETHER_STAR"
      },
      {
        "value": "Items.NETHER_STAR"
      },
      {
        "value": "Items.NETHER_STAR"
      },
      {
        "value": "Items.NETHER_STAR"
      }
    ],
    "recipeReturnStack": {
      "value": "Items.DEBUG_STICK"
    },
    "name": "nether_star_debug_stick",
    "namespace": "mod"
  }
}